kubert/__init__.py
kubert/Client/Client.py
kubert/Client/__init__.py
kubert/Config/Config.py
kubert/Config/__init__.py
kubert/WatchManger/WatchManger.py
kubert/WatchManger/__init__.py
kubert-0.0.8.dist-info/METADATA
kubert-0.0.8.dist-info/WHEEL
kubert-0.0.8.dist-info/top_level.txt
kubert-0.0.8.dist-info/RECORD
